{"files":{"Stillwell.md":{"filePath":"Stillwell.md","links":[],"meta":null,"parentNote":"index.md","title":"Stillwell","url":"Stillwell"},"Stillwell/Ch1.md":{"filePath":"Stillwell/Ch1.md","links":[],"meta":null,"parentNote":"Stillwell.md","title":"Ch1","url":"Stillwell/Ch1"},"Stillwell/Ch1/Ex3.org":{"filePath":"Stillwell/Ch1/Ex3.org","links":[],"meta":{"tags":[]},"parentNote":"Stillwell/Ch1.md","title":"Ex3","url":"Stillwell/Ch1/Ex3"},"Tao.md":{"filePath":"Tao.md","links":[],"meta":null,"parentNote":"index.md","title":"Tao","url":"Tao"},"Tao/Appendix.md":{"filePath":"Tao/Appendix.md","links":[],"meta":null,"parentNote":"Tao.md","title":"Appendix","url":"Tao/Appendix"},"Tao/Appendix/Appendix.org":{"filePath":"Tao/Appendix/Appendix.org","links":[],"meta":{"tags":[]},"parentNote":"Tao/Appendix.md","title":"Appendix","url":"Tao/Appendix/Appendix"},"Tao/Appendix/AxiomOfEquality.org":{"filePath":"Tao/Appendix/AxiomOfEquality.org","links":[],"meta":{"tags":[]},"parentNote":"Tao/Appendix.md","title":"Axiom Of Equality","url":"Tao/Appendix/AxiomOfEquality"},"Tao/chapter2.md":{"filePath":"Tao/chapter2.md","links":[],"meta":null,"parentNote":"Tao.md","title":"chapter2","url":"Tao/chapter2"},"Tao/chapter2/Exercise.md":{"filePath":"Tao/chapter2/Exercise.md","links":[],"meta":null,"parentNote":"Tao/chapter2.md","title":"Exercise","url":"Tao/chapter2/Exercise"},"Tao/chapter2/Exercise/exercise-2.2.1.org":{"filePath":"Tao/chapter2/Exercise/exercise-2.2.1.org","links":[{"resolvedRelTarget":{"contents":"Tao/chapter2/proposition-2.2.5","tag":"RRTFound"},"unresolvedRelTarget":{"contents":{"contents":{"contents":"Tao/chapter2/proposition-2.2.5.org","tag":"LMLRoute_Org"},"tag":"ModelRoute_LML"},"tag":"URTResource"}},{"resolvedRelTarget":{"contents":"Tao/chapter2/definition-2.2.1","tag":"RRTFound"},"unresolvedRelTarget":{"contents":{"contents":{"contents":"Tao/chapter2/definition-2.2.1.org","tag":"LMLRoute_Org"},"tag":"ModelRoute_LML"},"tag":"URTResource"}},{"resolvedRelTarget":{"contents":"Tao/chapter2/definition-2.2.1","tag":"RRTFound"},"unresolvedRelTarget":{"contents":{"contents":{"contents":"Tao/chapter2/definition-2.2.1.org","tag":"LMLRoute_Org"},"tag":"ModelRoute_LML"},"tag":"URTResource"}}],"meta":{"tags":[]},"parentNote":"Tao/chapter2/Exercise.md","title":"Exercise 2.2.1 (Proposition 2.2.5)","url":"Tao/chapter2/Exercise/exercise-2.2.1"},"Tao/chapter2/Exercise/exercise-2.2.2.org":{"filePath":"Tao/chapter2/Exercise/exercise-2.2.2.org","links":[{"resolvedRelTarget":{"contents":"Tao/chapter2/lemma-2.2.10","tag":"RRTFound"},"unresolvedRelTarget":{"contents":{"contents":{"contents":"Tao/chapter2/lemma-2.2.10.org","tag":"LMLRoute_Org"},"tag":"ModelRoute_LML"},"tag":"URTResource"}},{"resolvedRelTarget":{"contents":"Tao/chapter2/axiom-2.4","tag":"RRTFound"},"unresolvedRelTarget":{"contents":{"contents":{"contents":"Tao/chapter2/axiom-2.4.org","tag":"LMLRoute_Org"},"tag":"ModelRoute_LML"},"tag":"URTResource"}},{"resolvedRelTarget":{"contents":"Tao/Appendix/AxiomOfEquality","tag":"RRTFound"},"unresolvedRelTarget":{"contents":{"contents":{"contents":"Tao/Appendix/AxiomOfEquality.org","tag":"LMLRoute_Org"},"tag":"ModelRoute_LML"},"tag":"URTResource"}},{"resolvedRelTarget":{"contents":"Tao/Appendix/AxiomOfEquality","tag":"RRTFound"},"unresolvedRelTarget":{"contents":{"contents":{"contents":"Tao/Appendix/AxiomOfEquality.org","tag":"LMLRoute_Org"},"tag":"ModelRoute_LML"},"tag":"URTResource"}},{"resolvedRelTarget":{"contents":"Tao/Appendix/AxiomOfEquality","tag":"RRTFound"},"unresolvedRelTarget":{"contents":{"contents":{"contents":"Tao/Appendix/AxiomOfEquality.org","tag":"LMLRoute_Org"},"tag":"ModelRoute_LML"},"tag":"URTResource"}}],"meta":{"tags":[]},"parentNote":"Tao/chapter2/Exercise.md","title":"Exercise 2.2.2 (Lemma 2.2.10)","url":"Tao/chapter2/Exercise/exercise-2.2.2"},"Tao/chapter2/Exercise/exercise-2.2.3.org":{"filePath":"Tao/chapter2/Exercise/exercise-2.2.3.org","links":[{"resolvedRelTarget":{"contents":"Tao/chapter2/proposition-2.2.12","tag":"RRTFound"},"unresolvedRelTarget":{"contents":{"contents":{"contents":"Tao/chapter2/proposition-2.2.12.org","tag":"LMLRoute_Org"},"tag":"ModelRoute_LML"},"tag":"URTResource"}}],"meta":{"tags":[]},"parentNote":"Tao/chapter2/Exercise.md","title":"Exercise 2.2.3 (Propostion 2.2.12)","url":"Tao/chapter2/Exercise/exercise-2.2.3"},"Tao/chapter2/Exercise/exercise-2.2.4.org":{"filePath":"Tao/chapter2/Exercise/exercise-2.2.4.org","links":[{"resolvedRelTarget":{"contents":"Tao/chapter2/proposition-2.2.13","tag":"RRTFound"},"unresolvedRelTarget":{"contents":{"contents":{"contents":"Tao/chapter2/proposition-2.2.13.org","tag":"LMLRoute_Org"},"tag":"ModelRoute_LML"},"tag":"URTResource"}}],"meta":{"tags":[]},"parentNote":"Tao/chapter2/Exercise.md","title":"Exercise 2.2.4 (Propostion 2.2.13)","url":"Tao/chapter2/Exercise/exercise-2.2.4"},"Tao/chapter2/Exercise/exercise-2.2.5.org":{"filePath":"Tao/chapter2/Exercise/exercise-2.2.5.org","links":[],"meta":{"tags":[]},"parentNote":"Tao/chapter2/Exercise.md","title":"Exercise 2.2.5 (Proposition 2.2.14)","url":"Tao/chapter2/Exercise/exercise-2.2.5"},"Tao/chapter2/Exercise/exercise-2.3.1.org":{"filePath":"Tao/chapter2/Exercise/exercise-2.3.1.org","links":[{"resolvedRelTarget":{"contents":"Tao/chapter2/proposition-2.2.4","tag":"RRTFound"},"unresolvedRelTarget":{"contents":{"contents":{"contents":"Tao/chapter2/proposition-2.2.4.org","tag":"LMLRoute_Org"},"tag":"ModelRoute_LML"},"tag":"URTResource"}},{"resolvedRelTarget":{"contents":"Tao/chapter2/lemma-2.3.2","tag":"RRTFound"},"unresolvedRelTarget":{"contents":{"contents":{"contents":"Tao/chapter2/lemma-2.3.2.org","tag":"LMLRoute_Org"},"tag":"ModelRoute_LML"},"tag":"URTResource"}},{"resolvedRelTarget":{"contents":"Tao/chapter2/lemma-2.2.3","tag":"RRTFound"},"unresolvedRelTarget":{"contents":{"contents":{"contents":"Tao/chapter2/lemma-2.2.3.org","tag":"LMLRoute_Org"},"tag":"ModelRoute_LML"},"tag":"URTResource"}},{"resolvedRelTarget":{"contents":"Tao/chapter2/lemma-2.2.2","tag":"RRTFound"},"unresolvedRelTarget":{"contents":{"contents":{"contents":"Tao/chapter2/lemma-2.2.2.org","tag":"LMLRoute_Org"},"tag":"ModelRoute_LML"},"tag":"URTResource"}}],"meta":{"tags":[]},"parentNote":"Tao/chapter2/Exercise.md","title":"Exercise 2.3.1 (Lemma 2.3.2)","url":"Tao/chapter2/Exercise/exercise-2.3.1"},"Tao/chapter2/Exercise/exercise-2.3.2.org":{"filePath":"Tao/chapter2/Exercise/exercise-2.3.2.org","links":[],"meta":{"tags":[]},"parentNote":"Tao/chapter2/Exercise.md","title":"Exercise 2.3.2 (Lemma 2.3.3 )","url":"Tao/chapter2/Exercise/exercise-2.3.2"},"Tao/chapter2/axiom-2.1.org":{"filePath":"Tao/chapter2/axiom-2.1.org","links":[],"meta":{"tags":[]},"parentNote":"Tao/chapter2.md","title":"Axiom 2.1","url":"Tao/chapter2/axiom-2.1"},"Tao/chapter2/axiom-2.2.org":{"filePath":"Tao/chapter2/axiom-2.2.org","links":[],"meta":{"tags":[]},"parentNote":"Tao/chapter2.md","title":"Axiom 2.2","url":"Tao/chapter2/axiom-2.2"},"Tao/chapter2/axiom-2.3.org":{"filePath":"Tao/chapter2/axiom-2.3.org","links":[],"meta":{"tags":[]},"parentNote":"Tao/chapter2.md","title":"Axiom 2.3","url":"Tao/chapter2/axiom-2.3"},"Tao/chapter2/axiom-2.4.org":{"filePath":"Tao/chapter2/axiom-2.4.org","links":[],"meta":{"tags":[]},"parentNote":"Tao/chapter2.md","title":"Axiom 2.4","url":"Tao/chapter2/axiom-2.4"},"Tao/chapter2/axiom-2.5.org":{"filePath":"Tao/chapter2/axiom-2.5.org","links":[],"meta":{"tags":[]},"parentNote":"Tao/chapter2.md","title":"Axiom 2.5","url":"Tao/chapter2/axiom-2.5"},"Tao/chapter2/definition-2.2.1.org":{"filePath":"Tao/chapter2/definition-2.2.1.org","links":[],"meta":{"tags":[]},"parentNote":"Tao/chapter2.md","title":"Definition 2.2.1","url":"Tao/chapter2/definition-2.2.1"},"Tao/chapter2/lemma-2.2.10.org":{"filePath":"Tao/chapter2/lemma-2.2.10.org","links":[],"meta":{"tags":[]},"parentNote":"Tao/chapter2.md","title":"Lemma 2.2.10","url":"Tao/chapter2/lemma-2.2.10"},"Tao/chapter2/lemma-2.2.2.org":{"filePath":"Tao/chapter2/lemma-2.2.2.org","links":[],"meta":{"tags":[]},"parentNote":"Tao/chapter2.md","title":"Lemma 2.2.2","url":"Tao/chapter2/lemma-2.2.2"},"Tao/chapter2/lemma-2.2.3.org":{"filePath":"Tao/chapter2/lemma-2.2.3.org","links":[],"meta":{"tags":[]},"parentNote":"Tao/chapter2.md","title":"Lemma 2.2.3","url":"Tao/chapter2/lemma-2.2.3"},"Tao/chapter2/lemma-2.3.2.org":{"filePath":"Tao/chapter2/lemma-2.3.2.org","links":[],"meta":{"tags":[]},"parentNote":"Tao/chapter2.md","title":"Lemma 2.3.2","url":"Tao/chapter2/lemma-2.3.2"},"Tao/chapter2/proposition-2.2.12.org":{"filePath":"Tao/chapter2/proposition-2.2.12.org","links":[],"meta":{"tags":[]},"parentNote":"Tao/chapter2.md","title":"Proposition 2.2.12","url":"Tao/chapter2/proposition-2.2.12"},"Tao/chapter2/proposition-2.2.13.org":{"filePath":"Tao/chapter2/proposition-2.2.13.org","links":[],"meta":{"tags":[]},"parentNote":"Tao/chapter2.md","title":"Proposition 2.2.13","url":"Tao/chapter2/proposition-2.2.13"},"Tao/chapter2/proposition-2.2.14.org":{"filePath":"Tao/chapter2/proposition-2.2.14.org","links":[],"meta":{"tags":[]},"parentNote":"Tao/chapter2.md","title":"Proposition 2.2.14","url":"Tao/chapter2/proposition-2.2.14"},"Tao/chapter2/proposition-2.2.4.org":{"filePath":"Tao/chapter2/proposition-2.2.4.org","links":[],"meta":{"tags":[]},"parentNote":"Tao/chapter2.md","title":"Proposition 2.2.4","url":"Tao/chapter2/proposition-2.2.4"},"Tao/chapter2/proposition-2.2.5.org":{"filePath":"Tao/chapter2/proposition-2.2.5.org","links":[],"meta":{"tags":[]},"parentNote":"Tao/chapter2.md","title":"Proposition 2.2.5","url":"Tao/chapter2/proposition-2.2.5"},"index.md":{"filePath":"index.md","links":[{"resolvedRelTarget":{"contents":"-/tags","tag":"RRTFound"},"unresolvedRelTarget":{"contents":{"contents":[],"tag":"VirtualRoute_TagIndex"},"tag":"URTVirtual"}},{"resolvedRelTarget":{"contents":"-/all","tag":"RRTFound"},"unresolvedRelTarget":{"contents":{"tag":"VirtualRoute_Index"},"tag":"URTVirtual"}}],"meta":{"page":{"description":"We are a group of people who study Mathematics together. We are not professional Mathemacians but mostly scientists, engineers, and programmers."},"tags":[]},"parentNote":null,"title":"Sosu","url":""}},"version":1}